discord_drive/__init__.py
discord_drive/_discord_drive.py
discord_drive/_drive.py
discord_drive/_utils.py
discord_drive-0.0.11.dist-info/LICENSE.md
discord_drive-0.0.11.dist-info/METADATA
discord_drive-0.0.11.dist-info/WHEEL
discord_drive-0.0.11.dist-info/top_level.txt
discord_drive-0.0.11.dist-info/RECORD
